{
  "last_updated": "2026-01-07 12:22:04",
  "status": "running",
  "logs": [
    {
      "timestamp": "2026-01-07 12:21:38",
      "message": "Reprocessing: Lenovo launches new ThinkSystem servers dedicated to AI inference"
    },
    {
      "timestamp": "2026-01-07 12:21:39",
      "message": "[SKIP] Content too short: Lenovo launches new ThinkSyste..."
    },
    {
      "timestamp": "2026-01-07 12:21:40",
      "message": "Reprocessing: AI lending startup Pluto Financial raises $8.6M to unlock illiquid private equity capital"
    },
    {
      "timestamp": "2026-01-07 12:21:42",
      "message": "[SKIP] Content too short: AI lending startup Pluto Finan..."
    },
    {
      "timestamp": "2026-01-07 12:21:43",
      "message": "Reprocessing: CES 2026 decoded: Join theCUBE Jan. 13 for key insights"
    },
    {
      "timestamp": "2026-01-07 12:21:45",
      "message": "[SKIP] Content too short: CES 2026 decoded: Join theCUBE..."
    },
    {
      "timestamp": "2026-01-07 12:21:46",
      "message": "Reprocessing: Hyundai and Boston Dynamics join forces to bring humanoid robots to factories"
    },
    {
      "timestamp": "2026-01-07 12:21:47",
      "message": "[SKIP] Content too short: Hyundai and Boston Dynamics jo..."
    },
    {
      "timestamp": "2026-01-07 12:21:49",
      "message": "Reprocessing: Exabeam targets AI agent risk with connected, AI-driven security workflows"
    },
    {
      "timestamp": "2026-01-07 12:21:50",
      "message": "[SKIP] Content too short: Exabeam targets AI agent risk ..."
    },
    {
      "timestamp": "2026-01-07 12:21:51",
      "message": "Reprocessing: Vibe\u2019s new AI robot sits in on meetings to record every interaction and delegate tasks"
    },
    {
      "timestamp": "2026-01-07 12:21:53",
      "message": "[SKIP] Content too short: Vibe\u2019s new AI robot sits in on..."
    },
    {
      "timestamp": "2026-01-07 12:21:54",
      "message": "Reprocessing: Broadcom debuts new chips for powering Wi-Fi 8 access points"
    },
    {
      "timestamp": "2026-01-07 12:21:55",
      "message": "[SKIP] Content too short: Broadcom debuts new chips for ..."
    },
    {
      "timestamp": "2026-01-07 12:21:57",
      "message": "Reprocessing: Ambiq debuts first energy-optimized NPU chipset for advanced AI on battery-powered devices"
    },
    {
      "timestamp": "2026-01-07 12:21:58",
      "message": "[SKIP] Content too short: Ambiq debuts first energy-opti..."
    },
    {
      "timestamp": "2026-01-07 12:22:00",
      "message": "Reprocessing: Dell unveils new Alienware gaming PCs oozing power and style"
    },
    {
      "timestamp": "2026-01-07 12:22:01",
      "message": "[SKIP] Content too short: Dell unveils new Alienware gam..."
    },
    {
      "timestamp": "2026-01-07 12:22:03",
      "message": "Reprocessing: AMD launches Ryzen AI PC, data center, mobile and embedded processors at CES"
    },
    {
      "timestamp": "2026-01-07 12:22:04",
      "message": "[SKIP] Content too short: AMD launches Ryzen AI PC, data..."
    }
  ]
}