{
  "last_updated": "2026-01-07 09:12:44",
  "status": "running",
  "logs": [
    {
      "timestamp": "2026-01-07 09:12:09",
      "message": "[SUCCESS] Processed: \uc5f0\uac04 \uae00\ub85c\ubc8c IC \ud339 \ubc0f \uc2dc\uc124 \ubcf4\uace0\uc11c\n  > Summary: \ubc18\ub3c4\uccb4 \uae30\uc5c5\ub4e4\uc774 2025\ub144\uc758 \ub9ce\uc740 \uc2dc\uc124 \ud22c\uc790\ub97c \ubc1c\ud45c\ud588\uc2b5\ub2c8\ub2e4. \uc774 \ubcf4\uace0\uc11c\ub294 \uc778\uacf5\uc9c0\ub2a5 \uce69\uacfc \uace0..."
    },
    {
      "timestamp": "2026-01-07 09:12:10",
      "message": "[PROCESSING] Analyzing: Thermal Scanning-Probe Lithography in vdW Heterostructures (TU Denmark)..."
    },
    {
      "timestamp": "2026-01-07 09:12:12",
      "message": "[SKIP] Irrelevant (AI Filter): Thermal Scanning-Probe Lithography in vdW Heterostructures (TU Denmark)"
    },
    {
      "timestamp": "2026-01-07 09:12:13",
      "message": "Reprocessing: NXP Advances Edge AI Leadership with New eIQ Agentic AI Framework"
    },
    {
      "timestamp": "2026-01-07 09:12:15",
      "message": "[PROCESSING] Analyzing: NXP Advances Edge AI Leadership with New eIQ Agentic AI Framework..."
    },
    {
      "timestamp": "2026-01-07 09:12:20",
      "message": "[SUCCESS] Processed: NXP, \uc0c8\ub85c\uc6b4 eIQ \uc5d0\uc774\uc804\ud2f1 AI \ud504\ub808\uc784\uc6cc\ud06c\ub85c \uc5e3\uc9c0 AI \ub9ac\ub354\uc2ed \uac15\ud654\n  > Summary: NXP \ubc18\ub3c4\uccb4\ub294 \uc548\uc804\ud558\uace0 \uc2e4\uc2dc\uac04 \uc5e3\uc9c0 AI\ub97c \uc704\ud55c \uc0c8\ub85c\uc6b4 eIQ \uc5d0\uc774\uc804\ud2f1 AI \ud504\ub808\uc784\uc6cc\ud06c\ub97c..."
    },
    {
      "timestamp": "2026-01-07 09:12:21",
      "message": "[PROCESSING] Analyzing: Tianma and Universal Display Corporation Enter into Long-Term OLED Agreements..."
    },
    {
      "timestamp": "2026-01-07 09:12:23",
      "message": "[SKIP] Irrelevant (AI Filter): Tianma and Universal Display Corporation Enter into Long-Term OLED Agreements"
    },
    {
      "timestamp": "2026-01-07 09:12:24",
      "message": "[PROCESSING] Analyzing: HSC Appoints New Chief Operating Officer..."
    },
    {
      "timestamp": "2026-01-07 09:12:26",
      "message": "[SKIP] Irrelevant (AI Filter): HSC Appoints New Chief Operating Officer"
    },
    {
      "timestamp": "2026-01-07 09:12:28",
      "message": "Reprocessing: NXP Unveils S32N7 Central Processor for SDVs"
    },
    {
      "timestamp": "2026-01-07 09:12:29",
      "message": "[PROCESSING] Analyzing: NXP Unveils S32N7 Central Processor for SDVs..."
    },
    {
      "timestamp": "2026-01-07 09:12:34",
      "message": "[SUCCESS] Processed: NXP\uac00 SDV\ub97c \uc704\ud55c S32N7 \uc911\uc559 \ucc98\ub9ac\uae30\ub97c \uacf5\uac1c\ud558\ub2e4\n  > Summary: NXP \ubc18\ub3c4\uccb4\uac00 \uc18c\ud504\ud2b8\uc6e8\uc5b4 \uc815\uc758 \ucc28\ub7c9(SDV) \uac1c\ubc1c\uc744 \uc9c0\uc6d0\ud558\ub294 S32N7 \ud504\ub85c\uc138\uc11c \uc2dc\ub9ac\uc988\ub97c..."
    },
    {
      "timestamp": "2026-01-07 09:12:35",
      "message": "[PROCESSING] Analyzing: \ub9c8\uc774\ud06c\ub85c \ub9e4\ub2c8\uc9d5\uc77c\uae4c, \ub514\ud14c\uc77c\ud55c \uad00\ub9ac\uc77c\uae4c?..."
    },
    {
      "timestamp": "2026-01-07 09:12:37",
      "message": "[SKIP] Irrelevant (AI Filter): \ub9c8\uc774\ud06c\ub85c \ub9e4\ub2c8\uc9d5\uc77c\uae4c, \ub514\ud14c\uc77c\ud55c \uad00\ub9ac\uc77c\uae4c?"
    },
    {
      "timestamp": "2026-01-07 09:12:38",
      "message": "[PROCESSING] Analyzing: \uc601\ud5a5\ub825 \uc5c6\ub294 PM..."
    },
    {
      "timestamp": "2026-01-07 09:12:40",
      "message": "[SKIP] Irrelevant (AI Filter): \uc601\ud5a5\ub825 \uc5c6\ub294 PM"
    },
    {
      "timestamp": "2026-01-07 09:12:42",
      "message": "Reprocessing: PitchBook: AI dominates global venture capital as 2025 deal value nears record"
    },
    {
      "timestamp": "2026-01-07 09:12:43",
      "message": "[SKIP] Content too short: PitchBook: AI dominates global..."
    },
    {
      "timestamp": "2026-01-07 09:12:44",
      "message": "Reprocessing: Amazon\u2019s AI agents spark backlash from retailers after listing their products without permission"
    }
  ]
}