{
  "last_updated": "2026-01-09 15:29:14",
  "status": "running",
  "logs": [
    {
      "timestamp": "2026-01-09 15:28:41",
      "message": "[SKIP] Irrelevant (AI Filter): EE Awards Asia: Mapping Five Years of Electronics Innovation"
    },
    {
      "timestamp": "2026-01-09 15:28:43",
      "message": "[PROCESSING] Analyzing: Manufacturing Contracts for 10th Month in December..."
    },
    {
      "timestamp": "2026-01-09 15:28:45",
      "message": "[SKIP] Irrelevant (AI Filter): Manufacturing Contracts for 10th Month in December"
    },
    {
      "timestamp": "2026-01-09 15:28:46",
      "message": "[PROCESSING] Analyzing: What Colocation Providers Do \u2013 and Don\u2019t Do \u2013 for Your Infrastructure..."
    },
    {
      "timestamp": "2026-01-09 15:28:48",
      "message": "[SKIP] Irrelevant (AI Filter): What Colocation Providers Do \u2013 and Don\u2019t Do \u2013 for Your Infrastructure"
    },
    {
      "timestamp": "2026-01-09 15:28:49",
      "message": "[PROCESSING] Analyzing: Exploring the Practical Benefits of Carrier-Neutral Colocation..."
    },
    {
      "timestamp": "2026-01-09 15:28:51",
      "message": "[SKIP] Irrelevant (AI Filter): Exploring the Practical Benefits of Carrier-Neutral Colocation"
    },
    {
      "timestamp": "2026-01-09 15:28:52",
      "message": "[PROCESSING] Analyzing: Data Center Compliance in 2026: What Changed, What\u2019s Next, and How to Prepare..."
    },
    {
      "timestamp": "2026-01-09 15:28:54",
      "message": "[SKIP] Irrelevant (AI Filter): Data Center Compliance in 2026: What Changed, What\u2019s Next, and How to Prepare"
    },
    {
      "timestamp": "2026-01-09 15:28:56",
      "message": "[PROCESSING] Analyzing: GTR Secures $2B to Supercharge European Data Center Expansion..."
    },
    {
      "timestamp": "2026-01-09 15:28:58",
      "message": "[SKIP] Irrelevant (AI Filter): GTR Secures $2B to Supercharge European Data Center Expansion"
    },
    {
      "timestamp": "2026-01-09 15:28:59",
      "message": "[PROCESSING] Analyzing: Rain, which helps businesses issue stablecoin-linked Visa cards, raised a $250M Series C led by ICONIQ at a $1.95B valuation, taking its total funding to $338M+ (Pragyan Kalita/Reuters)..."
    },
    {
      "timestamp": "2026-01-09 15:29:02",
      "message": "[SKIP] Irrelevant (AI Filter): Rain, which helps businesses issue stablecoin-linked Visa cards, raised a $250M Series C led by ICONIQ at a $1.95B valuation, taking its total funding to $338M+ (Pragyan Kalita/Reuters)"
    },
    {
      "timestamp": "2026-01-09 15:29:03",
      "message": "[PROCESSING] Analyzing: X is restricting Grok's image capabilities via the @grok command for free users, but they can still create sexual deepfakes via X's \"Edit image\" or Grok's app (Robert Hart/The Verge)..."
    },
    {
      "timestamp": "2026-01-09 15:29:05",
      "message": "[SKIP] Irrelevant (AI Filter): X is restricting Grok's image capabilities via the @grok command for free users, but they can still create sexual deepfakes via X's \"Edit image\" or Grok's app (Robert Hart/The Verge)"
    },
    {
      "timestamp": "2026-01-09 15:29:07",
      "message": "[PROCESSING] Analyzing: The EU says it is considering designating WhatsApp a \"very large platform\", after WhatsApp published user numbers above the DSA threshold in February 2025 (Louise Breusch Rasmussen/Reuters)..."
    },
    {
      "timestamp": "2026-01-09 15:29:09",
      "message": "[SKIP] Irrelevant (AI Filter): The EU says it is considering designating WhatsApp a \"very large platform\", after WhatsApp published user numbers above the DSA threshold in February 2025 (Louise Breusch Rasmussen/Reuters)"
    },
    {
      "timestamp": "2026-01-09 15:29:11",
      "message": "[PROCESSING] Analyzing: a16z raises $15B+ across five new funds, including $6.75B for its fifth growth fund, the largest sum, and $3B for unspecified \"other venture strategies\" (Dan Primack/Axios)..."
    },
    {
      "timestamp": "2026-01-09 15:29:13",
      "message": "[SKIP] Irrelevant (AI Filter): a16z raises $15B+ across five new funds, including $6.75B for its fifth growth fund, the largest sum, and $3B for unspecified \"other venture strategies\" (Dan Primack/Axios)"
    },
    {
      "timestamp": "2026-01-09 15:29:14",
      "message": "[PROCESSING] Analyzing: Filings: X's UK revenue fell 58.3% YoY from \u00a369.1M in 2023 to \u00a328.9M in 2024; pre-tax profit fell from \u00a38.5M in 2022 and \u00a32.2M in 2023 to \u00a3767K in 2024 (Mark Sweney/The Guardian)..."
    }
  ]
}