{
  "last_updated": "2026-01-07 21:07:34",
  "status": "running",
  "logs": [
    {
      "timestamp": "2026-01-07 21:07:19",
      "message": "Starting automatic background collection..."
    },
    {
      "timestamp": "2026-01-07 21:07:20",
      "message": "Initializing..."
    },
    {
      "timestamp": "2026-01-07 21:07:20",
      "message": "Fetching RSS feeds..."
    },
    {
      "timestamp": "2026-01-07 21:07:34",
      "message": "Found 145 articles within the last 2 days. Starting processing..."
    },
    {
      "timestamp": "2026-01-07 21:07:34",
      "message": "[PROCESSING] Analyzing: L\u2019Or\u00e9al\u2019s latest flat iron uses infrared light to make hairstyling much faster..."
    }
  ]
}