{
  "last_updated": "2026-01-03 23:37:06",
  "status": "running",
  "logs": [
    {
      "timestamp": "2026-01-03 23:36:25",
      "message": "Found 42 articles within the last 2 days. Starting processing..."
    },
    {
      "timestamp": "2026-01-03 23:36:25",
      "message": "[PROCESSING] Analyzing: This smart home controller is literally a piece of wood..."
    },
    {
      "timestamp": "2026-01-03 23:36:28",
      "message": "[SKIP] Irrelevant (AI Filter): This smart home controller is literally a piece of wood"
    },
    {
      "timestamp": "2026-01-03 23:36:30",
      "message": "Reprocessing: CES 2026: all the news, gadgets, and innovations from the biggest tech show"
    },
    {
      "timestamp": "2026-01-03 23:36:31",
      "message": "[PROCESSING] Analyzing: CES 2026: all the news, gadgets, and innovations from the biggest tech show..."
    },
    {
      "timestamp": "2026-01-03 23:36:34",
      "message": "[SKIP] Irrelevant (AI Filter): CES 2026: all the news, gadgets, and innovations from the biggest tech show"
    },
    {
      "timestamp": "2026-01-03 23:36:35",
      "message": "[PROCESSING] Analyzing: Grok is undressing anyone, including minors..."
    },
    {
      "timestamp": "2026-01-03 23:36:38",
      "message": "[SKIP] Irrelevant (AI Filter): Grok is undressing anyone, including minors"
    },
    {
      "timestamp": "2026-01-03 23:36:39",
      "message": "[PROCESSING] Analyzing: Billion-dollar Bitcoin hacker Ilya Lichtenstein thanks Trump for early prison release..."
    },
    {
      "timestamp": "2026-01-03 23:36:42",
      "message": "[SKIP] Irrelevant (AI Filter): Billion-dollar Bitcoin hacker Ilya Lichtenstein thanks Trump for early prison release"
    },
    {
      "timestamp": "2026-01-03 23:36:44",
      "message": "Reprocessing: This smart fridge wants to solve the hassle of grocery shopping"
    },
    {
      "timestamp": "2026-01-03 23:36:45",
      "message": "[PROCESSING] Analyzing: This smart fridge wants to solve the hassle of grocery shopping..."
    },
    {
      "timestamp": "2026-01-03 23:36:48",
      "message": "[SKIP] Irrelevant (AI Filter): This smart fridge wants to solve the hassle of grocery shopping"
    },
    {
      "timestamp": "2026-01-03 23:36:50",
      "message": "[PROCESSING] Analyzing: Pebble\u2019s round smartwatch is getting a reboot..."
    },
    {
      "timestamp": "2026-01-03 23:36:52",
      "message": "[SKIP] Irrelevant (AI Filter): Pebble\u2019s round smartwatch is getting a reboot"
    },
    {
      "timestamp": "2026-01-03 23:36:54",
      "message": "Reprocessing: LG announces the &#8216;world\u2019s lightest 17-inch RTX laptop&#8217;"
    },
    {
      "timestamp": "2026-01-03 23:36:56",
      "message": "[PROCESSING] Analyzing: LG announces the &#8216;world\u2019s lightest 17-inch RTX laptop&#8217;..."
    },
    {
      "timestamp": "2026-01-03 23:37:01",
      "message": "[SUCCESS] Processed: LG\uac00 '\uc138\uacc4\uc5d0\uc11c \uac00\uc7a5 \uac00\ubcbc\uc6b4 17\uc778\uce58 RTX \ub178\ud2b8\ubd81'\uc744 \ubc1c\ud45c\ud558\ub2e4\n  > Summary: LG\ub294 CES\uc5d0\uc11c 2026\ub144 Gram Pro \uc2dc\ub9ac\uc988 \ub178\ud2b8\ubd81\uc744 \uc18c\uac1c\ud560 \uc608\uc815\uc785\ub2c8\ub2e4. \uc774 \uc2dc\ub9ac\uc988..."
    },
    {
      "timestamp": "2026-01-03 23:37:03",
      "message": "[PROCESSING] Analyzing: Fender\u2019s first wireless headphones have a long-lasting, replaceable battery..."
    },
    {
      "timestamp": "2026-01-03 23:37:06",
      "message": "[SKIP] Irrelevant (AI Filter): Fender\u2019s first wireless headphones have a long-lasting, replaceable battery"
    }
  ]
}